sig_rnn/__init__.py
sig_rnn/sig_gru.py
sig_rnn/sig_lstm.py
sig_rnn-0.1.0.dist-info/METADATA
sig_rnn-0.1.0.dist-info/WHEEL
sig_rnn-0.1.0.dist-info/RECORD
