Metadata-Version: 2.1
Name: sig_rnn
Version: 0.1.0
Summary: Signature gated RNN
Author: Rémi Genet
Requires-Python: >=3.9,<3.13
Classifier: Programming Language :: Python :: 3
Classifier: Programming Language :: Python :: 3.9
Classifier: Programming Language :: Python :: 3.10
Classifier: Programming Language :: Python :: 3.11
Classifier: Programming Language :: Python :: 3.12
Requires-Dist: jaxtyping (>=0.2.36,<0.3.0)
Requires-Dist: keras (>=3.0.0,<4.0)
Requires-Dist: keras-sig (>=1.0.1,<2.0.0)
